km_search_tui/__init__.py
km_search_tui/entry_points.py
km_search_tui/km_search_all_words_20251216_163914.txt
km_search_tui-0.0.9.data/data/share/km-search-tui/MasterDit.shp
km_search_tui-0.0.9.dist-info/METADATA
km_search_tui-0.0.9.dist-info/WHEEL
km_search_tui-0.0.9.dist-info/entry_points.txt
km_search_tui-0.0.9.dist-info/licenses/LICENSE
km_search_tui-0.0.9.dist-info/RECORD
