Metadata-Version: 2.4
Name: km-search-tui
Version: 0.0.9
Summary: 空明码查询工具 - 使用 Textual 开发的 TUI 应用，可以查询编码和中文的对应关系
License-File: LICENSE
Requires-Python: >=3.14
Requires-Dist: duckdb>=1.4.3
Requires-Dist: textual-dev>=1.8.0
Requires-Dist: textual>=6.8.0
